pipepal/__init__.py
pipepal/app.py
pipepal/audio/__init__.py
pipepal/audio/pipes/.gitkeep
pipepal/audio/tasks/__init__.py
pipepal/audio/tasks/example_task/__init__.py
pipepal/audio/tasks/example_task/abstract_service.py
pipepal/audio/tasks/example_task/interface.py
pipepal/audio/tasks/example_task/schemas/run/input.json
pipepal/audio/tasks/example_task/schemas/run/output.json
pipepal/audio/tasks/example_task/services/__init__.py
pipepal/audio/tasks/example_task/services/example_service/__init__.py
pipepal/audio/tasks/example_task/services/example_service/config.json
pipepal/audio/tasks/example_task/services/example_service/service.py
pipepal/audio/tasks/input_output/__init__.py
pipepal/audio/tasks/input_output/abstract_service.py
pipepal/audio/tasks/input_output/interface.py
pipepal/audio/tasks/input_output/schemas/read_HF_dataset_from_HF_hub/input.json
pipepal/audio/tasks/input_output/schemas/read_HF_dataset_from_HF_hub/output.json
pipepal/audio/tasks/input_output/schemas/read_audios_from_disk/input.json
pipepal/audio/tasks/input_output/schemas/read_audios_from_disk/output.json
pipepal/audio/tasks/input_output/schemas/read_local_HF_dataset/input.json
pipepal/audio/tasks/input_output/schemas/read_local_HF_dataset/output.json
pipepal/audio/tasks/input_output/schemas/save_HF_dataset_to_disk/input.json
pipepal/audio/tasks/input_output/schemas/save_HF_dataset_to_disk/output.json
pipepal/audio/tasks/input_output/schemas/upload_HF_dataset_to_HF_hub copy 2/input.json
pipepal/audio/tasks/input_output/schemas/upload_HF_dataset_to_HF_hub copy 2/output.json
pipepal/audio/tasks/input_output/services/__init__.py
pipepal/audio/tasks/input_output/services/datasets/__init__.py
pipepal/audio/tasks/input_output/services/datasets/config.json
pipepal/audio/tasks/input_output/services/datasets/service.py
pipepal/audio-cli/.gitkeep
pipepal/cli.py
pipepal/utils/__init__.py
pipepal/utils/abstract_component.py
pipepal/utils/functions.py
pipepal/video/__init__.py
pipepal-0.1.4.dist-info/LICENSE.txt
pipepal-0.1.4.dist-info/METADATA
pipepal-0.1.4.dist-info/WHEEL
pipepal-0.1.4.dist-info/entry_points.txt
pipepal-0.1.4.dist-info/RECORD
