Metadata-Version: 2.1
Name: pipepal
Version: 0.1.4
Summary: PipePal is a Python package that simplifies building pipelines for speech and voice analysis.
Home-page: https://github.com/sensein/pipepal
License: Apache-2.0
Keywords: voice,speech,audio
Author: Fabio Catania
Author-email: fabiocat@mit.edu
Maintainer: Fabio Catania
Maintainer-email: fabiocat@mit.edu
Requires-Python: >=3.10,<4.0
Classifier: Development Status :: 3 - Alpha
Classifier: License :: OSI Approved :: Apache Software License
Classifier: Operating System :: OS Independent
Classifier: Programming Language :: Python :: 3
Classifier: Programming Language :: Python :: 3.10
Classifier: Programming Language :: Python :: 3.11
Classifier: Programming Language :: Python :: 3.12
Requires-Dist: click (>=8.1.7,<9.0.0)
Requires-Dist: datasets (>=2.18.0,<3.0.0)
Requires-Dist: ffmpeg-python (>=0.2.0,<0.3.0)
Requires-Dist: ipykernel (>=6.29.4,<7.0.0)
Requires-Dist: jsonschema (>=4.21.1,<5.0.0)
Requires-Dist: librosa (>=0.10.1,<0.11.0)
Requires-Dist: soundfile (>=0.12.1,<0.13.0)
Requires-Dist: torch (>=2.2.2,<3.0.0)
Requires-Dist: torchaudio (>=2.2.2,<3.0.0)
Requires-Dist: torchvision (>=0.17.2,<0.18.0)
Requires-Dist: transformers (>=4.39.3,<5.0.0)
Project-URL: Documentation, https://sensein.github.io/pipepal
Project-URL: Repository, https://github.com/sensein/pipepal
